{
  "date": "2026-03-30T23:32:00Z",
  "thread_branch": "task-task_34eb435c387",
  "commit_scope": "spec(self-balancing-graph): operational proof — trend, proof ledger, 80% trigger, convergence validation",
  "files_owned": [
    "docs/system_audit/commit_evidence_2026-03-30_self-balancing-graph.json",
    "specs/self-balancing-graph.md"
  ],
  "local_validation": {
    "status": "pass",
    "details": "Spec written addressing the 'is it working?' question with GET /api/graph/health/trend, GET /api/graph/health/proof, GET /api/graph/health/convergence/{id}, tightened 80% surface_signal trigger, rolling 200-entry snapshot history, 5 concrete verification scenarios. Passes validate_spec_quality.py."
  },
  "ci_validation": {
    "status": "pass",
    "details": "Spec-only change. Validation is limited to evidence and spec-quality gates."
  },
  "deploy_validation": {
    "status": "pass",
    "details": "Docs-only commit. No deployment artifact or runtime endpoint change is part of this task."
  },
  "phase_gate": {
    "can_move_next_phase": true
  },
  "idea_ids": [
    "self-balancing-graph"
  ],
  "spec_ids": [
    "self-balancing-graph"
  ],
  "task_ids": [
    "task_34eb435c3873f117"
  ],
  "contributors": [
    {
      "contributor_id": "minimax-m2.7-cloud",
      "contributor_type": "machine",
      "roles": [
        "Product Management",
        "Specification"
      ]
    }
  ],
  "agent": {
    "name": "minimax-m2.7-cloud",
    "version": "cloud"
  },
  "evidence_refs": [
    "specs/172-fractal-self-balance.md",
    "specs/fractal-self-balance.md",
    "api/app/services/graph_health_service.py",
    "api/tests/test_172_graph_health.py"
  ],
  "change_files": [
    "docs/system_audit/commit_evidence_2026-03-30_self-balancing-graph.json",
    "specs/self-balancing-graph.md"
  ],
  "change_intent": "docs_only"
}
