{
  "generated_at_utc": "2026-03-10T22:15:25Z",
  "run_id": "post_merge_main_5dc7fe9_20260310T221525Z",
  "branch": "codex/mvp-baseline-post-merge-20260310",
  "origin_main_sha": "5dc7fe92e5cb0d6ff809ac3ac37d9066bcff10aa",
  "validation_scope": "local_only",
  "source_command": "./scripts/run_mvp_local_baseline.sh",
  "local_bases": {
    "api": "http://127.0.0.1:18145",
    "web": "http://127.0.0.1:3245"
  },
  "mvp_checklist": [
    {
      "id": "task_loop",
      "description": "task creation/execution/review loop",
      "status": "pass"
    },
    {
      "id": "idea_confidence_value_cost",
      "description": "idea confidence/value/cost updates surfaces reachable",
      "status": "pass"
    },
    {
      "id": "dashboard_visibility",
      "description": "dashboard/status visibility and links",
      "status": "pass"
    }
  ],
  "checks": {
    "api": {
      "health": 200,
      "ideas": 200,
      "tasks": 200,
      "system_lineage": 200,
      "runtime_endpoints_summary": 200
    },
    "web": {
      "root": 200,
      "ideas": 200,
      "specs": 200,
      "flow": 200,
      "tasks": 200,
      "gates": 200,
      "contribute": 200,
      "api_health": 200
    }
  },
  "result": "pass"
}
